kurenai/__init__.py
kurenai/__main__.py
kurenai/rouge_scorer.py
kurenai/tokenizers.py
kurenai-0.0.3.dist-info/licenses/LICENSE
kurenai-0.0.3.dist-info/METADATA
kurenai-0.0.3.dist-info/WHEEL
kurenai-0.0.3.dist-info/top_level.txt
kurenai-0.0.3.dist-info/RECORD
